{
	"tags": null,
	"alpha": 8,
	"beta": 1.2,
	"radius": 12.294488648222876,
	"target": [
		0,
		0,
		0
	],
	"inertialAlphaOffset": 0,
	"inertialBetaOffset": 0,
	"inertialRadiusOffset": 0,
	"lowerBetaLimit": 0.01,
	"upperBetaLimit": 3.1315926535897933,
	"inertialPanningX": 0,
	"inertialPanningY": 0,
	"pinchToPanMaxDistance": 20,
	"panningOriginTarget": [
		0,
		0,
		0
	],
	"panningInertia": 0.9,
	"zoomOnFactor": 1,
	"targetScreenOffset": {
		"x": 0,
		"y": 0
	},
	"allowUpsideDown": true,
	"useInputToRestoreState": true,
	"rotation": [
		0,
		0,
		0
	],
	"speed": 2,
	"position": [
		-1.6672767339000627,
		4.455003299008996,
		11.337000706522677
	],
	"upVector": [
		0,
		1,
		0
	],
	"fov": 1,
	"minZ": 1,
	"maxZ": 43920.75720520019,
	"inertia": 0.9,
	"mode": 0,
	"layerMask": 268435455,
	"fovMode": 0,
	"cameraRigMode": 0,
	"name": "PlayerCamera",
	"id": "33cde3a9-6817-4bf7-a702-d27eacd79602",
	"state": "",
	"metadata": {
		"script": {
			"name": "src/scenes/scene/Camera.ts"
		}
	},
	"type": "ArcRotateCamera",
	"parentId": "7d1b16cf-8642-40e7-8ce5-c9b0eaea95e2",
	"inputsmgr": {
		"ArcRotateCameraKeyboardMoveInput": {
			"tags": null,
			"keysUp": [
				38
			],
			"keysDown": [
				40
			],
			"keysLeft": [
				37
			],
			"keysRight": [
				39
			],
			"keysReset": [
				220
			],
			"panningSensibility": 50,
			"zoomingSensibility": 25,
			"useAltToZoom": true,
			"angularSpeed": 0.01
		},
		"ArcRotateCameraMouseWheelInput": {
			"tags": null,
			"wheelPrecision": 3,
			"wheelDeltaPercentage": 0
		},
		"ArcRotateCameraPointersInput": {
			"tags": null,
			"buttons": [
				0,
				1,
				2
			],
			"angularSensibilityX": 1000,
			"angularSensibilityY": 1000,
			"pinchPrecision": 12,
			"pinchDeltaPercentage": 0,
			"useNaturalPinchZoom": false,
			"panningSensibility": 1000,
			"multiTouchPanning": true,
			"multiTouchPanAndZoom": true
		}
	},
	"animations": [],
	"ranges": []
}